bids2openminds/__init__.py
bids2openminds/converter.py
bids2openminds/main.py
bids2openminds/mapping.py
bids2openminds/report.py
bids2openminds/utility.py
bids2openminds-0.1.1.dist-info/licenses/AUTHORS
bids2openminds-0.1.1.dist-info/licenses/LICENSE
bids2openminds-0.1.1.dist-info/METADATA
bids2openminds-0.1.1.dist-info/WHEEL
bids2openminds-0.1.1.dist-info/entry_points.txt
bids2openminds-0.1.1.dist-info/top_level.txt
bids2openminds-0.1.1.dist-info/RECORD
