Metadata-Version: 2.4
Name: bids2openminds
Version: 0.1.1
Summary: Generates openMINDS metadata from a BIDS dataset
Author-email: Peyman Najafi <peyman.najafi@cnrs.fr>, "Andrew P. Davison" <andrew.davison@cnrs.fr>, Lyuba Zehl <lyuba.zehl@ebrains.eu>
License: MIT License
Classifier: Development Status :: 3 - Alpha
Classifier: Programming Language :: Python
Requires-Python: >=3.9
License-File: LICENSE
License-File: AUTHORS
Requires-Dist: bids-validator==1.14.6
Requires-Dist: bids
Requires-Dist: openminds>=0.2.3
Requires-Dist: click>=8.1
Requires-Dist: pandas
Requires-Dist: nameparser>=1.1.3
Provides-Extra: test
Requires-Dist: pytest; extra == "test"
Requires-Dist: pytest-cov; extra == "test"
Dynamic: license-file
